fastapi_keycloak_auth-lib/__init__.py
fastapi_keycloak_auth-lib/auth.py
fastapi_keycloak_auth-lib/config.py
fastapi_keycloak_auth-lib/decorators.py
fastapi_keycloak_auth-lib/exceptions.py
fastapi_keycloak_auth_lib/__init__.py
fastapi_keycloak_auth_lib/auth.py
fastapi_keycloak_auth_lib/config.py
fastapi_keycloak_auth_lib/decorators.py
fastapi_keycloak_auth_lib/exceptions.py
fastapi_keycloak_auth_lib-0.1.12.dist-info/LICENSE
fastapi_keycloak_auth_lib-0.1.12.dist-info/METADATA
fastapi_keycloak_auth_lib-0.1.12.dist-info/WHEEL
fastapi_keycloak_auth_lib-0.1.12.dist-info/top_level.txt
fastapi_keycloak_auth_lib-0.1.12.dist-info/RECORD
