Metadata-Version: 2.2
Name: fastapi-keycloak-auth-lib
Version: 0.1.12
Summary: FastAPI integration with Keycloak for authentication and role-based access control
Home-page: https://github.com/your-username/fastapi-keycloak-auth
Author: shareef
Author-email: your.email@example.com
Classifier: Programming Language :: Python :: 3
Classifier: License :: OSI Approved :: MIT License
Classifier: Operating System :: OS Independent
Requires-Python: >=3.7
License-File: LICENSE
Requires-Dist: requests
Requires-Dist: fastapi
Requires-Dist: cryptography
Requires-Dist: authlib
Requires-Dist: python-dotenv
Dynamic: author
Dynamic: author-email
Dynamic: classifier
Dynamic: description
Dynamic: description-content-type
Dynamic: home-page
Dynamic: requires-dist
Dynamic: requires-python
Dynamic: summary
